p6plab/__init__.py
p6plab/azure_pricing_mcp_server/__init__.py
p6plab/azure_pricing_mcp_server/server.py
p6plab_azure_pricing_mcp_server-1.4.0.dist-info/METADATA
p6plab_azure_pricing_mcp_server-1.4.0.dist-info/WHEEL
p6plab_azure_pricing_mcp_server-1.4.0.dist-info/entry_points.txt
p6plab_azure_pricing_mcp_server-1.4.0.dist-info/licenses/LICENSE
p6plab_azure_pricing_mcp_server-1.4.0.dist-info/licenses/NOTICE
p6plab_azure_pricing_mcp_server-1.4.0.dist-info/RECORD
