Metadata-Version: 2.4
Name: p6plab.azure-pricing-mcp-server
Version: 1.4.0
Summary: A P6P Lab Model Context Protocol (MCP) server for Azure pricing analysis
Author: P6P Lab
Author-email: P6P Lab MCP <peepeepopapapeepeepo+pypi-azure-pricing-mcp-server@gmail.com>
License: Apache-2.0
License-File: LICENSE
License-File: NOTICE
Classifier: License :: OSI Approved :: Apache Software License
Classifier: Operating System :: OS Independent
Classifier: Programming Language :: Python
Classifier: Programming Language :: Python :: 3
Classifier: Programming Language :: Python :: 3.10
Classifier: Programming Language :: Python :: 3.11
Classifier: Programming Language :: Python :: 3.12
Classifier: Programming Language :: Python :: 3.13
Requires-Python: >=3.10
Requires-Dist: bs4>=0.0.2
Requires-Dist: httpx>=0.25.0
Requires-Dist: mcp[cli]>=1.6.0
Requires-Dist: pydantic>=2.10.6
Requires-Dist: pytest-asyncio>=0.23.0
Requires-Dist: pytest>=7.4.0
Requires-Dist: typing-extensions>=4.8.0
